querypanda/__init__.py
querypanda/performance_stats.py
querypanda/querypanda.py
querypanda-0.2.2.dist-info/LICENSE
querypanda-0.2.2.dist-info/METADATA
querypanda-0.2.2.dist-info/WHEEL
querypanda-0.2.2.dist-info/top_level.txt
querypanda-0.2.2.dist-info/RECORD
