Metadata-Version: 2.1
Name: querypanda
Version: 0.2.2
Summary: From SQL queries to pandas DataFrames: QueryPanda makes it easy to retrieve, aggregate, and save data from PostgreSQL, enhancing data analysis and machine learning projects.
Author-email: Shashank Goud <shashaankgoud@gmail.com>
License: MIT License
Project-URL: Homepage, https://github.com/Shazankk/QueryPanda
Project-URL: Repository, https://github.com/Shazankk/QueryPanda
Classifier: Development Status :: 3 - Alpha
Classifier: Intended Audience :: Developers
Classifier: Natural Language :: English
Classifier: Programming Language :: Python :: 3
Classifier: Programming Language :: Python :: 3.8
Classifier: Programming Language :: Python :: 3.9
Classifier: Programming Language :: Python :: 3.10
Classifier: Programming Language :: Python :: 3.11
Classifier: Programming Language :: Python :: 3.12
Classifier: License :: OSI Approved :: MIT License
Classifier: Operating System :: OS Independent
Requires-Python: >=3.8
License-File: LICENSE
Requires-Dist: pandas >=1.2.0
Requires-Dist: psycopg2-binary >=2.8.6
Requires-Dist: openpyxl >=3.0.5
